{
    "title": "60대 이후, 절대 곁에 두면 안 되는 사람 유형 3가지",
    "segments": [
        {
            "text": "나이가 들수록 사람은 가려 사귀어야 합니다. 특히 60대 이후엔 '에너지 뱀파이어'를 쳐내야 남은 인생이 편안해집니다.",
            "image_path": "/Users/mac/.gemini/antigravity/playground/deep-rocket/shorts_factory/assets/img_friend_01.png"
        },
        {
            "text": "첫째, 만나면 아픈 소리, 힘든 소리만 늘어놓는 사람입니다. 내 기운까지 뺏어가는 이런 사람은 동정심 갖지 말고 과감히 멀리하십시오.",
            "image_path": "/Users/mac/.gemini/antigravity/playground/deep-rocket/shorts_factory/assets/img_friend_02.png"
        },
        {
            "text": "둘째, '왕년에 내가 말이야'하며 자식 자랑, 돈 자랑만 하는 사람입니다. 들어주는 것도 한두 번입니다. 당신의 귀한 노년을 감정 쓰레기통으로 만들지 마세요.",
            "image_path": "/Users/mac/.gemini/antigravity/playground/deep-rocket/shorts_factory/assets/img_friend_03.png"
        },
        {
            "text": "셋째, 남 잘되는 꼴 못 보고 깎아내리기 바쁜 사람입니다. 곁에 두면 의심과 불행만 전염될 뿐입니다. 질투는 노년을 추하게 만듭니다.",
            "image_path": "/Users/mac/.gemini/antigravity/playground/deep-rocket/shorts_factory/assets/img_friend_04.png"
        },
        {
            "text": "친구는 양보다 질입니다. 혼자가 되는 것을 두려워 마세요. 나를 웃게 만드는 사람만 곁에 두기에도 짧고 소중한 인생입니다.",
            "image_path": "/Users/mac/.gemini/antigravity/playground/deep-rocket/shorts_factory/assets/img_friend_05.png"
        }
    ],
    "bgm_path": null
}